[
  {
    "id": "2125bd65-342d-4390-b889-384fbaef680c",
    "name": "Cindy Hessel",
    "phone": "468.898.5467",
    "email": "Lori_Little96@gmail.com",
    "job": "Human Tactics Consultant"
  },
  {
    "id": "c48d848f-da45-4e5f-ad96-34587f6ce891",
    "name": "Louise Jenkins",
    "phone": "793.872.9473",
    "email": "Madonna96@gmail.com",
    "job": "Global Metrics Developer"
  },
  {
    "id": "2bea8920-386e-4e04-9d86-78b088f8f986",
    "name": "Penny Klocko-Cronin",
    "phone": "1-943-444-3576",
    "email": "Gerard81@gmail.com",
    "job": "Forward Paradigm Associate"
  },
  {
    "id": "c422beee-4e7c-4296-a6b6-3e7b8988330a",
    "name": "Audrey Langosh",
    "phone": "896-811-9741 x699",
    "email": "Jacky70@gmail.com",
    "job": "National Data Consultant"
  },
  {
    "id": "f94237a9-67e3-4eb3-af5c-b008a5784e2c",
    "name": "Gregg Parisian",
    "phone": "1-523-720-4364 x57869",
    "email": "Eleazar.Murazik@gmail.com",
    "job": "District Directives Engineer"
  }
]